pymtl3_prbs/__init__.py
pymtl3_prbs/utils.py
pymtl3_prbs/lfsr/LfsrFL.py
pymtl3_prbs/lfsr/LfsrGeneric.py
pymtl3_prbs/lfsr/__init__.py
pymtl3_prbs/lfsr/test/LfsrFL_test.py
pymtl3_prbs/lfsr/test/LfsrGeneric_test.py
pymtl3_prbs/lfsr/test/__init__.py
pymtl3_prbs/prbs/PatternGenerator.py
pymtl3_prbs/prbs/PatternVerifier.py
pymtl3_prbs/prbs/__init__.py
pymtl3_prbs/prbs/test/PatternGenerator_test.py
pymtl3_prbs/prbs/test/PatternVerifier_test.py
pymtl3_prbs/prbs/test/__init__.py
pymtl3_prbs/prbs/test/pg_pv_compositon_test.py
pymtl3_prbs-0.0.0.dist-info/METADATA
pymtl3_prbs-0.0.0.dist-info/WHEEL
pymtl3_prbs-0.0.0.dist-info/top_level.txt
pymtl3_prbs-0.0.0.dist-info/RECORD
